MANIFEST.in
README.rst
setup.cfg
setup.py
versioneer.py
wlcsim/__init__.py
wlcsim/_version.py
wlcsim/data.py
wlcsim/fortran_parser.py
wlcsim/input.py
wlcsim/plot.py
wlcsim/plot_wlcsim.py
wlcsim/tests.py
wlcsim.egg-info/PKG-INFO
wlcsim.egg-info/SOURCES.txt
wlcsim.egg-info/dependency_links.txt
wlcsim.egg-info/requires.txt
wlcsim.egg-info/top_level.txt
wlcsim/FrankElastic/Yplot.py
wlcsim/FrankElastic/__init__.py
wlcsim/FrankElastic/frank.py
wlcsim/FrankElastic/invlaplace.py
wlcsim/FrankElastic/plot_frank.py
wlcsim/FrankElastic/rigidrod.py
wlcsim/FrankElastic/stonefence.py
wlcsim/FrankElastic/yyyreal.py
wlcsim/analytical/__init__.py
wlcsim/analytical/fractional.py
wlcsim/analytical/homolog.py
wlcsim/analytical/rouse.py
wlcsim/analytical/wlc.py
wlcsim/bd/__init__.py
wlcsim/bd/forces.py
wlcsim/bd/homolog.py
wlcsim/bd/init_beads.py
wlcsim/bd/rouse.py
wlcsim/bd/runge_kutta.py
wlcsim/bd/spheres_in_sphere.py
wlcsim/bd/tsswlc.py
wlcsim/chains/__init__.py
wlcsim/chains/rouse.py
wlcsim/chains/wlc.py
wlcsim/mc/__init__.py
wlcsim/mc/box_insertion.py
wlcsim/mc/sphere_insertion.py
wlcsim/special/__init__.py
wlcsim/special/homolog_process.py
wlcsim/tabulation/__init__.py
wlcsim/tabulation/dssWLCparams
wlcsim/tabulation/vvcf_table.csv
wlcsim/utils/__init__.py
wlcsim/utils/cached_property.py
wlcsim/utils/collisions.py
wlcsim/utils/coltimes.py
wlcsim/utils/exampleSimpleMapReduce.py
wlcsim/utils/math.py
wlcsim/utils/multiprocessing_mapreduce.py
wlcsim/utils/path.py
wlcsim/utils/reshape_old_runs.py
wlcsim/utils/rotation.py
wlcsim/utils/utils.py