Metadata-Version: 2.1
Name: wlcsim
Version: 0.1.6
Summary: UNKNOWN
Home-page: https://github.com/SpakowitzLab/BasicWLC
Author: Bruno Beltran
Author-email: brunobeltran0@gmail.com
License: UNKNOWN
Platform: UNKNOWN
Classifier: Intended Audience :: Science/Research
Classifier: Intended Audience :: Developers
Classifier: Development Status :: 2 - Pre-Alpha
Classifier: License :: OSI Approved :: MIT License
Classifier: Natural Language :: English
Classifier: Programming Language :: Python :: 3 :: Only
Classifier: Programming Language :: Fortran
Classifier: Topic :: Scientific/Engineering :: Chemistry
Classifier: Topic :: Scientific/Engineering :: Physics
